uart_tx2.v
`default_nettype none

module uart_tx2 (
    input       CLK,
    input       TX_DV,
    input [7:0] TX_BYTE,
    output      TX_DATA,
    output      DONE // done sending, ready for new data
);

    parameter UART_BAUD = 9600;
    // parameter UART_BAUD = 115200;
    // parameter UART_BAUD = 921600;
    parameter CLKS_PER_BIT = (12_000_000 / UART_BAUD);

    parameter IDLE    = 3'b000;
    parameter START   = 3'b001;
    parameter DATA    = 3'b010;
    parameter STOP    = 3'b011;
    parameter CLEANUP = 3'b100;

    // If new data available and done sending copy it in
    always @(posedge CLK) begin
        if (TX_DV && Done) begin
            Tx_Byte <= TX_BYTE;
        end
    end

    reg [7:0]  Tx_Byte     = 0;
    reg        Tx_Data     = 0;
    reg        Done        = 0;
    reg [2:0]  Bit_Idx     = 0;
    reg [31:0] Clock_Count = 0;
    reg [2:0]  State       = IDLE;

    always @(posedge CLK) begin
        case (State)
            IDLE: begin
                Tx_Data     <= 1; // idle high
                Done        <= 1;
                Bit_Idx     <= 0;
                Clock_Count <= 0;

                if (TX_DV == 1) begin
                    State <= START;
                    Done <= 0;
                end
            end

            START: begin // send the start bit
                Tx_Data <= 0; // start bit
                Done <= 0;

                if (Clock_Count < CLKS_PER_BIT - 1 ) begin
                    Clock_Count <= Clock_Count + 1;
                end
                else begin
                    Clock_Count <= 0;
                    State <= DATA;
                end
            end

            DATA: begin
                Tx_Data <= Tx_Byte[Bit_Idx];

                if (Clock_Count < CLKS_PER_BIT - 1) begin
                    Clock_Count <= Clock_Count + 1;
                end
                else begin
                    Clock_Count <= 0;

                    if (Bit_Idx < 7) begin
                        Bit_Idx <= Bit_Idx + 1;
                    end
                    else begin
                        Bit_Idx <= 0;
                        State <= STOP;
                    end
                end
            end

            STOP: begin
                Tx_Data <= 1;

                if (Clock_Count < CLKS_PER_BIT - 1) begin
                    Clock_Count <= Clock_Count + 1;
                end
                else begin
                    State <= IDLE;
                end
            end

            default: begin
                State <= IDLE;
            end
        endcase
    end

    assign DONE    = Done;
    assign TX_DATA = Tx_Data;
endmodule

ram.v
`default_nettype none
module ram (DIN, WR_ADDR, WR_EN, CLK, RD_ADDR, DOUT);
    // 512x8 RAM, taken directly from Lattice ice40 memory programming guide
    parameter addr_width = 9;
    parameter data_width = 8;

    input [addr_width-1:0]  WR_ADDR;
    input [data_width-1:0]  DIN;
    input                   WR_EN;
    input                   CLK;
    input  [addr_width-1:0] RD_ADDR;
    output [data_width-1:0] DOUT;

    // The actual RAM hardware block is inferred here by the very large register
    // rather than being explicityly stated
    reg [data_width-1:0] DOUT; // Register for output.
    reg [data_width-1:0] mem[(1<<addr_width)-1:0];

    always @(posedge CLK) begin
        if (WR_EN)
            mem[WR_ADDR] <= DIN;
        DOUT <= mem[RD_ADDR]; // Output register controlled by clock.
    end

endmodule

uart_rx.v
// based on https://www.nandland.com/vhdl/modules/module-uart-serial-port-rs232.html

`default_nettype none
`timescale 1ns / 1ps

module uart_rx 
(
    input        SER_CLK,
    input        RX_SERIAL,
    output       RX_DV,
    output [7:0] RX_BYTE
);

    parameter UART_BAUD    = 9600;
    // parameter UART_BAUD    = 115200;
    // parameter UART_BAUD    = 921600;
    parameter CLKS_PER_BIT = (12_000_000 / UART_BAUD);

    parameter IDLE    = 3'b000;
    parameter START   = 3'b001;
    parameter DATA    = 3'b010;
    parameter STOP    = 3'b011;
    parameter CLEANUP = 3'b100;

    // NOTE: if clock counter doesn't have enough bits it can overflow
    // quite easily
    reg [31:0] Clock_Count = 0; 
    reg [2:0]  Bit_Idx     = 0;
    reg [7:0]  Rx_Byte     = 0;
    reg        Rx_Dv       = 0;
    reg [2:0]  State       = 0;
    reg        Rx_Data     = 1;

    always @(posedge SER_CLK) begin
        Rx_Data <= RX_SERIAL;
    end

    always @(posedge SER_CLK) begin
        case (State)
            IDLE: begin // no data on line
                Rx_Dv       <= 1'b0;
                Clock_Count <= 0;
                Bit_Idx     <= 0;

                // check for start bit
                if (Rx_Data == 0)
                    State <= START;
                else
                    State <= IDLE;
            end // IDLE

            START: begin // start bit detected
                if (Clock_Count == (CLKS_PER_BIT-1)/2) begin // wait to halfway through
                    if (Rx_Data == 0) begin                  // clock period, check
                        Clock_Count <= 0;                    // that start bit is still
                        State       <= DATA;                 // valid. If so, recieve
                    end                                      // the data
                end
                else begin                           // clock up to halfway through
                    Clock_Count <= Clock_Count + 1;  // the start bit
                    State       <= START;
                end
            end // START

            DATA: begin
                if (Clock_Count < CLKS_PER_BIT - 1) begin
                    Clock_Count <= Clock_Count + 1;
                    State       <= DATA;
                end
                else begin
                    Clock_Count      <= 0;
                    Rx_Byte[Bit_Idx] <= Rx_Data;
                    // more bits to recieve?
                    if (Bit_Idx < 7) begin
                        Bit_Idx <= Bit_Idx + 1;
                        State   <= DATA;
                    end
                    else begin
                        Bit_Idx <= 0;
                        State   <= STOP;
                    end
                end
            end // DATA

            STOP: begin
                if (Clock_Count < CLKS_PER_BIT - 1) begin // wait for stop bit to finish
                    Clock_Count <= Clock_Count + 1;
                    State       <= STOP;
                end
                else begin
                    Rx_Dv       <= 1'b1;
                    Clock_Count <= 0;
                    State       <= CLEANUP;
                end
            end // STOP

            CLEANUP: begin // pretty optional I think
                State <= IDLE;
                Rx_Dv <= 1'b0;
            end // CLEANUP

            default:
                State <= IDLE;
        endcase
    end
 
    assign RX_DV   = Rx_Dv;
    assign RX_BYTE = Rx_Byte;

endmodule

ram_test/test.v
`timescale 1ns / 10ps
// `include "uart_tx2.v"
// `include "uart_rx.v"
// `include "ram.v"

module test();
    // Testbench uses a 10 MHz clock
    // Want to interface to 115200 baud UART
    // 10000000 / 115200 = 87 Clocks Per Bit.
    parameter CLOCK_FREQ      = 10_000_000;
    parameter CLOCK_PERIOD_NS = 1_000_000_000 / CLOCK_FREQ;
    parameter CLOCKS_PER_BIT  = CLOCK_FREQ / 115200;

    reg clk = 0;
    always
        #(CLOCK_PERIOD_NS/2) clk <= !clk;

    reg        input_tx_dv = 0;
    reg [7:0]  input_tx_byte = 0;
    wire       input_tx_data;
    wire       input_tx_done;
    uart_tx2#(.CLKS_PER_BIT(CLOCKS_PER_BIT)) uart_input(clk,
                                                        input_tx_dv,
                                                        input_tx_byte,
                                                        input_tx_data,
                                                        input_tx_done);

    wire       rx_data;
    wire       rx_dv;
    wire [7:0] rx_byte;

    assign rx_data = input_tx_data;

    uart_rx #(.CLKS_PER_BIT(CLOCKS_PER_BIT)) rx(clk, rx_data, rx_dv, rx_byte);

    wire [7:0] ram_din;
    reg  [8:0] ram_wr_addr = 0;
    wire       ram_wr_en;
    reg  [8:0] ram_rd_addr = 0;
    wire [7:0] ram_dout;

    assign ram_din   = rx_byte;
    assign ram_wr_en = rx_dv;
    ram ram_inst(ram_din, ram_wr_addr, ram_wr_en, clk, ram_rd_addr, ram_dout);

    wire       tx_dv;
    wire [7:0] tx_byte;
    wire       tx_data;
    wire       tx_done;

    wire data_available = (ram_rd_addr <= ram_wr_addr);
    assign tx_dv   = (tx_done && data_available);
    assign tx_byte = ram_dout;

    uart_tx2#(.CLKS_PER_BIT(CLOCKS_PER_BIT)) uart_tx(clk,
                                                     tx_dv,
                                                     tx_byte,
                                                     tx_data,
                                                     tx_done);

    always @(posedge rx_dv) begin
        ram_wr_addr <= ram_wr_addr + 1;
    end

    always @(posedge tx_done) begin
        if (data_available)
            ram_rd_addr <= ram_rd_addr + 1;
    end

    reg [7:0] ii;
    initial begin
        $dumpfile("test.vcd");
        $dumpvars(0, test);
        @(posedge clk);
        @(posedge clk);

        input_tx_byte <= 8'h0F;
        input_tx_dv <= 1;
        @(posedge clk);
        input_tx_dv <= 0;
        @(posedge input_tx_done);

        input_tx_byte <= 8'hAA;
        input_tx_dv <= 1;
        @(posedge clk);
        input_tx_dv <= 0;
        @(posedge input_tx_done);

        input_tx_byte <= 8'h80;
        input_tx_dv <= 1;
        @(posedge clk);
        input_tx_dv <= 0;

        // for (ii = 0; ii < 100; ii++) begin
        //     $display(ii);
        //     input_tx_byte <= ii;
        //     input_tx_dv <= 1;
        //     @(posedge clk);
        //     input_tx_dv <= 0;
        //     @(posedge input_tx_done);
        // end

        @(posedge tx_done);
        #1000000
        $finish;
    end
endmodule

ram_test/test.vcd
$date
	Sun Apr 28 00:36:27 2019
$end
$version
	Icarus Verilog
$end
$timescale
	1ps
$end
$scope module test $end
$var wire 8 ! ram_din [7:0] $end
$var wire 1 " ram_wr_en $end
$var wire 1 # rx_data $end
$var wire 8 $ tx_byte [7:0] $end
$var wire 1 % tx_dv $end
$var wire 1 & tx_done $end
$var wire 1 ' tx_data $end
$var wire 1 ( rx_dv $end
$var wire 8 ) rx_byte [7:0] $end
$var wire 8 * ram_dout [7:0] $end
$var wire 1 + input_tx_done $end
$var wire 1 , input_tx_data $end
$var wire 1 - data_available $end
$var reg 1 . clk $end
$var reg 8 / input_tx_byte [7:0] $end
$var reg 1 0 input_tx_dv $end
$var reg 9 1 ram_rd_addr [8:0] $end
$var reg 9 2 ram_wr_addr [8:0] $end
$scope module ram_inst $end
$var wire 1 . CLK $end
$var wire 8 3 DIN [7:0] $end
$var wire 9 4 RD_ADDR [8:0] $end
$var wire 9 5 WR_ADDR [8:0] $end
$var wire 1 " WR_EN $end
$var reg 8 6 DOUT [7:0] $end
$upscope $end
$scope module rx $end
$var wire 1 # RX_SERIAL $end
$var wire 1 . SER_CLK $end
$var wire 1 ( RX_DV $end
$var wire 8 7 RX_BYTE [7:0] $end
$var reg 3 8 Bit_Idx [2:0] $end
$var reg 32 9 Clock_Count [31:0] $end
$var reg 8 : Rx_Byte [7:0] $end
$var reg 1 ; Rx_Data $end
$var reg 1 ( Rx_Dv $end
$var reg 3 < State [2:0] $end
$upscope $end
$scope module uart_input $end
$var wire 1 . CLK $end
$var wire 1 + DONE $end
$var wire 8 = TX_BYTE [7:0] $end
$var wire 1 0 TX_DV $end
$var wire 1 , TX_DATA $end
$var reg 3 > Bit_Idx [2:0] $end
$var reg 32 ? Clock_Count [31:0] $end
$var reg 1 @ Done $end
$var reg 3 A State [2:0] $end
$var reg 8 B Tx_Byte [7:0] $end
$var reg 1 , Tx_Data $end
$upscope $end
$scope module uart_tx $end
$var wire 1 . CLK $end
$var wire 8 C TX_BYTE [7:0] $end
$var wire 1 ' TX_DATA $end
$var wire 1 % TX_DV $end
$var wire 1 & DONE $end
$var reg 3 D Bit_Idx [2:0] $end
$var reg 32 E Clock_Count [31:0] $end
$var reg 1 & Done $end
$var reg 3 F State [2:0] $end
$var reg 8 G Tx_Byte [7:0] $end
$var reg 1 H Tx_Data $end
$upscope $end
$upscope $end
$enddefinitions $end
#0
$dumpvars
0H
b0 G
b0 F
b0 E
b0 D
bx C
b0 B
b0 A
0@
b0 ?
b0 >
b0 =
b0 <
1;
b0 :
b0 9
b0 8
b0 7
bx 6
b0 5
b0 4
b0 3
b0 2
b0 1
00
b0 /
0.
1-
0,
0+
bx *
b0 )
0(
0'
0&
0%
bx $
0#
0"
b0 !
$end
#50000
0-
b1 1
b1 4
0%
1+
1@
1#
1,
0;
1&
1'
1H
1.
#100000
0.
#150000
10
b1111 /
b1111 =
b1 <
1;
1.
#200000
0.
#250000
b1111 B
0+
0@
b1 A
b1 9
00
1.
#300000
0.
#350000
b10 9
b1 ?
0#
0,
1.
#400000
0.
#450000
b10 ?
0;
b11 9
1.
#500000
0.
#550000
b100 9
b11 ?
1.
#600000
0.
#650000
b100 ?
b101 9
1.
#700000
0.
#750000
b110 9
b101 ?
1.
#800000
0.
#850000
b110 ?
b111 9
1.
#900000
0.
#950000
b1000 9
b111 ?
1.
#1000000
0.
#1050000
b1000 ?
b1001 9
1.
#1100000
0.
#1150000
b1010 9
b1001 ?
1.
#1200000
0.
#1250000
b1010 ?
b1011 9
1.
#1300000
0.
#1350000
b1100 9
b1011 ?
1.
#1400000
0.
#1450000
b1100 ?
b1101 9
1.
#1500000
0.
#1550000
b1110 9
b1101 ?
1.
#1600000
0.
#1650000
b1110 ?
b1111 9
1.
#1700000
0.
#1750000
b10000 9
b1111 ?
1.
#1800000
0.
#1850000
b10000 ?
b10001 9
1.
#1900000
0.
#1950000
b10010 9
b10001 ?
1.
#2000000
0.
#2050000
b10010 ?
b10011 9
1.
#2100000
0.
#2150000
b10100 9
b10011 ?
1.
#2200000
0.
#2250000
b10100 ?
b10101 9
1.
#2300000
0.
#2350000
b10110 9
b10101 ?
1.
#2400000
0.
#2450000
b10110 ?
b10111 9
1.
#2500000
0.
#2550000
b11000 9
b10111 ?
1.
#2600000
0.
#2650000
b11000 ?
b11001 9
1.
#2700000
0.
#2750000
b11010 9
b11001 ?
1.
#2800000
0.
#2850000
b11010 ?
b11011 9
1.
#2900000
0.
#2950000
b11100 9
b11011 ?
1.
#3000000
0.
#3050000
b11100 ?
b11101 9
1.
#3100000
0.
#3150000
b11110 9
b11101 ?
1.
#3200000
0.
#3250000
b11110 ?
b11111 9
1.
#3300000
0.
#3350000
b100000 9
b11111 ?
1.
#3400000
0.
#3450000
b100000 ?
b100001 9
1.
#3500000
0.
#3550000
b100010 9
b100001 ?
1.
#3600000
0.
#3650000
b100010 ?
b100011 9
1.
#3700000
0.
#3750000
b100100 9
b100011 ?
1.
#3800000
0.
#3850000
b100100 ?
b100101 9
1.
#3900000
0.
#3950000
b100110 9
b100101 ?
1.
#4000000
0.
#4050000
b100110 ?
b100111 9
1.
#4100000
0.
#4150000
b101000 9
b100111 ?
1.
#4200000
0.
#4250000
b101000 ?
b101001 9
1.
#4300000
0.
#4350000
b101010 9
b101001 ?
1.
#4400000
0.
#4450000
b101010 ?
b10 <
b0 9
1.
#4500000
0.
#4550000
b1 9
b101011 ?
1.
#4600000
0.
#4650000
b101100 ?
b10 9
1.
#4700000
0.
#4750000
b11 9
b101101 ?
1.
#4800000
0.
#4850000
b101110 ?
b100 9
1.
#4900000
0.
#4950000
b101 9
b101111 ?
1.
#5000000
0.
#5050000
b110000 ?
b110 9
1.
#5100000
0.
#5150000
b111 9
b110001 ?
1.
#5200000
0.
#5250000
b110010 ?
b1000 9
1.
#5300000
0.
#5350000
b1001 9
b110011 ?
1.
#5400000
0.
#5450000
b110100 ?
b1010 9
1.
#5500000
0.
#5550000
b1011 9
b110101 ?
1.
#5600000
0.
#5650000
b110110 ?
b1100 9
1.
#5700000
0.
#5750000
b1101 9
b110111 ?
1.
#5800000
0.
#5850000
b111000 ?
b1110 9
1.
#5900000
0.
#5950000
b1111 9
b111001 ?
1.
#6000000
0.
#6050000
b111010 ?
b10000 9
1.
#6100000
0.
#6150000
b10001 9
b111011 ?
1.
#6200000
0.
#6250000
b111100 ?
b10010 9
1.
#6300000
0.
#6350000
b10011 9
b111101 ?
1.
#6400000
0.
#6450000
b111110 ?
b10100 9
1.
#6500000
0.
#6550000
b10101 9
b111111 ?
1.
#6600000
0.
#6650000
b1000000 ?
b10110 9
1.
#6700000
0.
#6750000
b10111 9
b1000001 ?
1.
#6800000
0.
#6850000
b1000010 ?
b11000 9
1.
#6900000
0.
#6950000
b11001 9
b1000011 ?
1.
#7000000
0.
#7050000
b1000100 ?
b11010 9
1.
#7100000
0.
#7150000
b11011 9
b1000101 ?
1.
#7200000
0.
#7250000
b1000110 ?
b11100 9
1.
#7300000
0.
#7350000
b11101 9
b1000111 ?
1.
#7400000
0.
#7450000
b1001000 ?
b11110 9
1.
#7500000
0.
#7550000
b11111 9
b1001001 ?
1.
#7600000
0.
#7650000
b1001010 ?
b100000 9
1.
#7700000
0.
#7750000
b100001 9
b1001011 ?
1.
#7800000
0.
#7850000
b1001100 ?
b100010 9
1.
#7900000
0.
#7950000
b100011 9
b1001101 ?
1.
#8000000
0.
#8050000
b1001110 ?
b100100 9
1.
#8100000
0.
#8150000
b100101 9
b1001111 ?
1.
#8200000
0.
#8250000
b1010000 ?
b100110 9
1.
#8300000
0.
#8350000
b100111 9
b1010001 ?
1.
#8400000
0.
#8450000
b1010010 ?
b101000 9
1.
#8500000
0.
#8550000
b101001 9
b1010011 ?
1.
#8600000
0.
#8650000
b1010100 ?
b101010 9
1.
#8700000
0.
#8750000
b101011 9
b1010101 ?
1.
#8800000
0.
#8850000
b10 A
b0 ?
b101100 9
1.
#8900000
0.
#8950000
b101101 9
b1 ?
1#
1,
1.
#9000000
0.
#9050000
b10 ?
1;
b101110 9
1.
#9100000
0.
#9150000
b101111 9
b11 ?
1.
#9200000
0.
#9250000
b100 ?
b110000 9
1.
#9300000
0.
#9350000
b110001 9
b101 ?
1.
#9400000
0.
#9450000
b110 ?
b110010 9
1.
#9500000
0.
#9550000
b110011 9
b111 ?
1.
#9600000
0.
#9650000
b1000 ?
b110100 9
1.
#9700000
0.
#9750000
b110101 9
b1001 ?
1.
#9800000
0.
#9850000
b1010 ?
b110110 9
1.
#9900000
0.
#9950000
b110111 9
b1011 ?
1.
#10000000
0.
#10050000
b1100 ?
b111000 9
1.
#10100000
0.
#10150000
b111001 9
b1101 ?
1.
#10200000
0.
#10250000
b1110 ?
b111010 9
1.
#10300000
0.
#10350000
b111011 9
b1111 ?
1.
#10400000
0.
#10450000
b10000 ?
b111100 9
1.
#10500000
0.
#10550000
b111101 9
b10001 ?
1.
#10600000
0.
#10650000
b10010 ?
b111110 9
1.
#10700000
0.
#10750000
b111111 9
b10011 ?
1.
#10800000
0.
#10850000
b10100 ?
b1000000 9
1.
#10900000
0.
#10950000
b1000001 9
b10101 ?
1.
#11000000
0.
#11050000
b10110 ?
b1000010 9
1.
#11100000
0.
#11150000
b1000011 9
b10111 ?
1.
#11200000
0.
#11250000
b11000 ?
b1000100 9
1.
#11300000
0.
#11350000
b1000101 9
b11001 ?
1.
#11400000
0.
#11450000
b11010 ?
b1000110 9
1.
#11500000
0.
#11550000
b1000111 9
b11011 ?
1.
#11600000
0.
#11650000
b11100 ?
b1001000 9
1.
#11700000
0.
#11750000
b1001001 9
b11101 ?
1.
#11800000
0.
#11850000
b11110 ?
b1001010 9
1.
#11900000
0.
#11950000
b1001011 9
b11111 ?
1.
#12000000
0.
#12050000
b100000 ?
b1001100 9
1.
#12100000
0.
#12150000
b1001101 9
b100001 ?
1.
#12200000
0.
#12250000
b100010 ?
b1001110 9
1.
#12300000
0.
#12350000
b1001111 9
b100011 ?
1.
#12400000
0.
#12450000
b100100 ?
b1010000 9
1.
#12500000
0.
#12550000
b1010001 9
b100101 ?
1.
#12600000
0.
#12650000
b100110 ?
b1010010 9
1.
#12700000
0.
#12750000
b1010011 9
b100111 ?
1.
#12800000
0.
#12850000
b101000 ?
b1010100 9
1.
#12900000
0.
#12950000
b1010101 9
b101001 ?
1.
#13000000
0.
#13050000
b101010 ?
b1 8
b1 !
b1 3
b1 )
b1 7
b1 :
b0 9
1.
#13100000
0.
#13150000
b1 9
b101011 ?
1.
#13200000
0.
#13250000
b101100 ?
b10 9
1.
#13300000
0.
#13350000
b11 9
b101101 ?
1.
#13400000
0.
#13450000
b101110 ?
b100 9
1.
#13500000
0.
#13550000
b101 9
b101111 ?
1.
#13600000
0.
#13650000
b110000 ?
b110 9
1.
#13700000
0.
#13750000
b111 9
b110001 ?
1.
#13800000
0.
#13850000
b110010 ?
b1000 9
1.
#13900000
0.
#13950000
b1001 9
b110011 ?
1.
#14000000
0.
#14050000
b110100 ?
b1010 9
1.
#14100000
0.
#14150000
b1011 9
b110101 ?
1.
#14200000
0.
#14250000
b110110 ?
b1100 9
1.
#14300000
0.
#14350000
b1101 9
b110111 ?
1.
#14400000
0.
#14450000
b111000 ?
b1110 9
1.
#14500000
0.
#14550000
b1111 9
b111001 ?
1.
#14600000
0.
#14650000
b111010 ?
b10000 9
1.
#14700000
0.
#14750000
b10001 9
b111011 ?
1.
#14800000
0.
#14850000
b111100 ?
b10010 9
1.
#14900000
0.
#14950000
b10011 9
b111101 ?
1.
#15000000
0.
#15050000
b111110 ?
b10100 9
1.
#15100000
0.
#15150000
b10101 9
b111111 ?
1.
#15200000
0.
#15250000
b1000000 ?
b10110 9
1.
#15300000
0.
#15350000
b10111 9
b1000001 ?
1.
#15400000
0.
#15450000
b1000010 ?
b11000 9
1.
#15500000
0.
#15550000
b11001 9
b1000011 ?
1.
#15600000
0.
#15650000
b1000100 ?
b11010 9
1.
#15700000
0.
#15750000
b11011 9
b1000101 ?
1.
#15800000
0.
#15850000
b1000110 ?
b11100 9
1.
#15900000
0.
#15950000
b11101 9
b1000111 ?
1.
#16000000
0.
#16050000
b1001000 ?
b11110 9
1.
#16100000
0.
#16150000
b11111 9
b1001001 ?
1.
#16200000
0.
#16250000
b1001010 ?
b100000 9
1.
#16300000
0.
#16350000
b100001 9
b1001011 ?
1.
#16400000
0.
#16450000
b1001100 ?
b100010 9
1.
#16500000
0.
#16550000
b100011 9
b1001101 ?
1.
#16600000
0.
#16650000
b1001110 ?
b100100 9
1.
#16700000
0.
#16750000
b100101 9
b1001111 ?
1.
#16800000
0.
#16850000
b1010000 ?
b100110 9
1.
#16900000
0.
#16950000
b100111 9
b1010001 ?
1.
#17000000
0.
#17050000
b1010010 ?
b101000 9
1.
#17100000
0.
#17150000
b101001 9
b1010011 ?
1.
#17200000
0.
#17250000
b1010100 ?
b101010 9
1.
#17300000
0.
#17350000
b101011 9
b1010101 ?
1.
#17400000
0.
#17450000
b1 >
b0 ?
b101100 9
1.
#17500000
0.
#17550000
b101101 9
b1 ?
1.
#17600000
0.
#17650000
b10 ?
b101110 9
1.
#17700000
0.
#17750000
b101111 9
b11 ?
1.
#17800000
0.
#17850000
b100 ?
b110000 9
1.
#17900000
0.
#17950000
b110001 9
b101 ?
1.
#18000000
0.
#18050000
b110 ?
b110010 9
1.
#18100000
0.
#18150000
b110011 9
b111 ?
1.
#18200000
0.
#18250000
b1000 ?
b110100 9
1.
#18300000
0.
#18350000
b110101 9
b1001 ?
1.
#18400000
0.
#18450000
b1010 ?
b110110 9
1.
#18500000
0.
#18550000
b110111 9
b1011 ?
1.
#18600000
0.
#18650000
b1100 ?
b111000 9
1.
#18700000
0.
#18750000
b111001 9
b1101 ?
1.
#18800000
0.
#18850000
b1110 ?
b111010 9
1.
#18900000
0.
#18950000
b111011 9
b1111 ?
1.
#19000000
0.
#19050000
b10000 ?
b111100 9
1.
#19100000
0.
#19150000
b111101 9
b10001 ?
1.
#19200000
0.
#19250000
b10010 ?
b111110 9
1.
#19300000
0.
#19350000
b111111 9
b10011 ?
1.
#19400000
0.
#19450000
b10100 ?
b1000000 9
1.
#19500000
0.
#19550000
b1000001 9
b10101 ?
1.
#19600000
0.
#19650000
b10110 ?
b1000010 9
1.
#19700000
0.
#19750000
b1000011 9
b10111 ?
1.
#19800000
0.
#19850000
b11000 ?
b1000100 9
1.
#19900000
0.
#19950000
b1000101 9
b11001 ?
1.
#20000000
0.
#20050000
b11010 ?
b1000110 9
1.
#20100000
0.
#20150000
b1000111 9
b11011 ?
1.
#20200000
0.
#20250000
b11100 ?
b1001000 9
1.
#20300000
0.
#20350000
b1001001 9
b11101 ?
1.
#20400000
0.
#20450000
b11110 ?
b1001010 9
1.
#20500000
0.
#20550000
b1001011 9
b11111 ?
1.
#20600000
0.
#20650000
b100000 ?
b1001100 9
1.
#20700000
0.
#20750000
b1001101 9
b100001 ?
1.
#20800000
0.
#20850000
b100010 ?
b1001110 9
1.
#20900000
0.
#20950000
b1001111 9
b100011 ?
1.
#21000000
0.
#21050000
b100100 ?
b1010000 9
1.
#21100000
0.
#21150000
b1010001 9
b100101 ?
1.
#21200000
0.
#21250000
b100110 ?
b1010010 9
1.
#21300000
0.
#21350000
b1010011 9
b100111 ?
1.
#21400000
0.
#21450000
b101000 ?
b1010100 9
1.
#21500000
0.
#21550000
b1010101 9
b101001 ?
1.
#21600000
0.
#21650000
b101010 ?
b10 8
b11 !
b11 3
b11 )
b11 7
b11 :
b0 9
1.
#21700000
0.
#21750000
b1 9
b101011 ?
1.
#21800000
0.
#21850000
b101100 ?
b10 9
1.
#21900000
0.
#21950000
b11 9
b101101 ?
1.
#22000000
0.
#22050000
b101110 ?
b100 9
1.
#22100000
0.
#22150000
b101 9
b101111 ?
1.
#22200000
0.
#22250000
b110000 ?
b110 9
1.
#22300000
0.
#22350000
b111 9
b110001 ?
1.
#22400000
0.
#22450000
b110010 ?
b1000 9
1.
#22500000
0.
#22550000
b1001 9
b110011 ?
1.
#22600000
0.
#22650000
b110100 ?
b1010 9
1.
#22700000
0.
#22750000
b1011 9
b110101 ?
1.
#22800000
0.
#22850000
b110110 ?
b1100 9
1.
#22900000
0.
#22950000
b1101 9
b110111 ?
1.
#23000000
0.
#23050000
b111000 ?
b1110 9
1.
#23100000
0.
#23150000
b1111 9
b111001 ?
1.
#23200000
0.
#23250000
b111010 ?
b10000 9
1.
#23300000
0.
#23350000
b10001 9
b111011 ?
1.
#23400000
0.
#23450000
b111100 ?
b10010 9
1.
#23500000
0.
#23550000
b10011 9
b111101 ?
1.
#23600000
0.
#23650000
b111110 ?
b10100 9
1.
#23700000
0.
#23750000
b10101 9
b111111 ?
1.
#23800000
0.
#23850000
b1000000 ?
b10110 9
1.
#23900000
0.
#23950000
b10111 9
b1000001 ?
1.
#24000000
0.
#24050000
b1000010 ?
b11000 9
1.
#24100000
0.
#24150000
b11001 9
b1000011 ?
1.
#24200000
0.
#24250000
b1000100 ?
b11010 9
1.
#24300000
0.
#24350000
b11011 9
b1000101 ?
1.
#24400000
0.
#24450000
b1000110 ?
b11100 9
1.
#24500000
0.
#24550000
b11101 9
b1000111 ?
1.
#24600000
0.
#24650000
b1001000 ?
b11110 9
1.
#24700000
0.
#24750000
b11111 9
b1001001 ?
1.
#24800000
0.
#24850000
b1001010 ?
b100000 9
1.
#24900000
0.
#24950000
b100001 9
b1001011 ?
1.
#25000000
0.
#25050000
b1001100 ?
b100010 9
1.
#25100000
0.
#25150000
b100011 9
b1001101 ?
1.
#25200000
0.
#25250000
b1001110 ?
b100100 9
1.
#25300000
0.
#25350000
b100101 9
b1001111 ?
1.
#25400000
0.
#25450000
b1010000 ?
b100110 9
1.
#25500000
0.
#25550000
b100111 9
b1010001 ?
1.
#25600000
0.
#25650000
b1010010 ?
b101000 9
1.
#25700000
0.
#25750000
b101001 9
b1010011 ?
1.
#25800000
0.
#25850000
b1010100 ?
b101010 9
1.
#25900000
0.
#25950000
b101011 9
b1010101 ?
1.
#26000000
0.
#26050000
b10 >
b0 ?
b101100 9
1.
#26100000
0.
#26150000
b101101 9
b1 ?
1.
#26200000
0.
#26250000
b10 ?
b101110 9
1.
#26300000
0.
#26350000
b101111 9
b11 ?
1.
#26400000
0.
#26450000
b100 ?
b110000 9
1.
#26500000
0.
#26550000
b110001 9
b101 ?
1.
#26600000
0.
#26650000
b110 ?
b110010 9
1.
#26700000
0.
#26750000
b110011 9
b111 ?
1.
#26800000
0.
#26850000
b1000 ?
b110100 9
1.
#26900000
0.
#26950000
b110101 9
b1001 ?
1.
#27000000
0.
#27050000
b1010 ?
b110110 9
1.
#27100000
0.
#27150000
b110111 9
b1011 ?
1.
#27200000
0.
#27250000
b1100 ?
b111000 9
1.
#27300000
0.
#27350000
b111001 9
b1101 ?
1.
#27400000
0.
#27450000
b1110 ?
b111010 9
1.
#27500000
0.
#27550000
b111011 9
b1111 ?
1.
#27600000
0.
#27650000
b10000 ?
b111100 9
1.
#27700000
0.
#27750000
b111101 9
b10001 ?
1.
#27800000
0.
#27850000
b10010 ?
b111110 9
1.
#27900000
0.
#27950000
b111111 9
b10011 ?
1.
#28000000
0.
#28050000
b10100 ?
b1000000 9
1.
#28100000
0.
#28150000
b1000001 9
b10101 ?
1.
#28200000
0.
#28250000
b10110 ?
b1000010 9
1.
#28300000
0.
#28350000
b1000011 9
b10111 ?
1.
#28400000
0.
#28450000
b11000 ?
b1000100 9
1.
#28500000
0.
#28550000
b1000101 9
b11001 ?
1.
#28600000
0.
#28650000
b11010 ?
b1000110 9
1.
#28700000
0.
#28750000
b1000111 9
b11011 ?
1.
#28800000
0.
#28850000
b11100 ?
b1001000 9
1.
#28900000
0.
#28950000
b1001001 9
b11101 ?
1.
#29000000
0.
#29050000
b11110 ?
b1001010 9
1.
#29100000
0.
#29150000
b1001011 9
b11111 ?
1.
#29200000
0.
#29250000
b100000 ?
b1001100 9
1.
#29300000
0.
#29350000
b1001101 9
b100001 ?
1.
#29400000
0.
#29450000
b100010 ?
b1001110 9
1.
#29500000
0.
#29550000
b1001111 9
b100011 ?
1.
#29600000
0.
#29650000
b100100 ?
b1010000 9
1.
#29700000
0.
#29750000
b1010001 9
b100101 ?
1.
#29800000
0.
#29850000
b100110 ?
b1010010 9
1.
#29900000
0.
#29950000
b1010011 9
b100111 ?
1.
#30000000
0.
#30050000
b101000 ?
b1010100 9
1.
#30100000
0.
#30150000
b1010101 9
b101001 ?
1.
#30200000
0.
#30250000
b101010 ?
b11 8
b111 !
b111 3
b111 )
b111 7
b111 :
b0 9
1.
#30300000
0.
#30350000
b1 9
b101011 ?
1.
#30400000
0.
#30450000
b101100 ?
b10 9
1.
#30500000
0.
#30550000
b11 9
b101101 ?
1.
#30600000
0.
#30650000
b101110 ?
b100 9
1.
#30700000
0.
#30750000
b101 9
b101111 ?
1.
#30800000
0.
#30850000
b110000 ?
b110 9
1.
#30900000
0.
#30950000
b111 9
b110001 ?
1.
#31000000
0.
#31050000
b110010 ?
b1000 9
1.
#31100000
0.
#31150000
b1001 9
b110011 ?
1.
#31200000
0.
#31250000
b110100 ?
b1010 9
1.
#31300000
0.
#31350000
b1011 9
b110101 ?
1.
#31400000
0.
#31450000
b110110 ?
b1100 9
1.
#31500000
0.
#31550000
b1101 9
b110111 ?
1.
#31600000
0.
#31650000
b111000 ?
b1110 9
1.
#31700000
0.
#31750000
b1111 9
b111001 ?
1.
#31800000
0.
#31850000
b111010 ?
b10000 9
1.
